README.md
setup.py
django_michael_jackson.egg-info/PKG-INFO
django_michael_jackson.egg-info/SOURCES.txt
django_michael_jackson.egg-info/dependency_links.txt
django_michael_jackson.egg-info/not-zip-safe
django_michael_jackson.egg-info/requires.txt
django_michael_jackson.egg-info/top_level.txt
michaeljackson/__init__.py
michaeljackson/data.py
michaeljackson/middleware.py
michaeljackson/tests/__init__.py
michaeljackson/tests/setup.py
michaeljackson/tests/test_middleware.py
michaeljackson/tests/urls.py
michaeljackson/tests/views.py